{
  "payload":{
    "id": 1,
    "name":"Condomínio Pedra do Sol",
    "type":"condominio",
    "address":{
      "street":"Rua Sebastião Lacerda",
      "number":"30",
      "district":"Laranjeiras",
      "city":"Rio de Janeiro",
      "state":"RJ",
      "zip":"22240-110",
      "country":"Brazil",
      "phone":"+55 21 2265-1758"
    },
    "blocks":[
      {
        "number":1,
        "name":"Bloco 1",
        "apartments":28,
        "floors":[
          {
            "number":1,
            "name":"Térreo",
            "controlled_lights":[
              {
                "id":"091fe207-f208-4eda-b985-e2d303aacfc9",
                "area":"Portaria R. Seb. Lacerda",
                "type":"reception",
                "connection":"online",
                "state":0,
                "stragegy":"economy"
              },
              {
                "id":"2677004c-0316-4ef9-9ce5-3ca0c6524a14",
                "area":"Portaria R. Condé de Avelar",
                "type":"reception",
                "connection":"online",
                "state":0,
                "stragegy":"scheduled"
              }
            ]
          },
          {
            "number":2,
            "name":"Playground",
            "controlled_lights":[
              {
                "id":"9bb5c405-e94b-478c-b40b-0cf8c5efc3a8",
                "area":"Playground Bloco 1",
                "type":"park",
                "connection":"online",
                "state":0,
                "stragegy":"manual"
              },
              {
                "id":"37cea9b8-2185-449a-becb-fd8e357c6f2a",
                "area":"Garagem G2",
                "type":"parking",
                "connection":"online",
                "state":0,
                "stragegy":"manual"
              },
              {
                "id":"ee1db8ac-6222-4da1-9a8e-0c20eeafb500",
                "area":"Piscina Semi-Olímpica",
                "type":"pool",
                "connection":"online",
                "state":0,
                "stragegy":"scheduled",
                "schedule":{
                  "mon":[
                    {
                      "set":1,
                      "time":"18:00:00-03:00"
                    },
                    {
                      "set":0,
                      "time":"03:00:00-03:00"
                    }
                  ],
                  "tue":[
                    {
                      "set":1,
                      "time":"18:00:00-03:00"
                    },
                    {
                      "set":0,
                      "time":"03:00:00-03:00"
                    }
                  ],
                  "wed":[
                    {
                      "set":1,
                      "time":"18:00:00-03:00"
                    },
                    {
                      "set":0,
                      "time":"03:00:00-03:00"
                    }
                  ],
                  "thu":[
                    {
                      "set":1,
                      "time":"18:00:00-03:00"
                    },
                    {
                      "set":0,
                      "time":"03:00:00-03:00"
                    }
                  ],
                  "fri":[
                    {
                      "set":1,
                      "time":"18:00:00-03:00"
                    },
                    {
                      "set":0,
                      "time":"03:00:00-03:00"
                    }
                  ],
                  "sat":[
                    {
                      "set":1,
                      "time":"18:00:00-03:00"
                    },
                    {
                      "set":0,
                      "time":"03:00:00-03:00"
                    }
                  ],
                  "sun":[
                    {
                      "set":1,
                      "time":"18:00:00-03:00"
                    },
                    {
                      "set":0,
                      "time":"03:00:00-03:00"
                    }
                  ]
                }
              }
            ]
          },
          {
            "number":3,
            "name":"Garagem G3",
            "controlled_lights":[
              {
                "id":"2023b8b7-b133-4ad0-989a-03a2b2b2b6b2",
                "area":"Luz do hall de garagem",
                "type":"hall",
                "connection":"online",
                "state":0,
                "stragegy":"manual"
              },
              {
                "id":"688c2e7e-26b3-47df-b07b-81ce9858f37a",
                "area":"Garagem G3",
                "type":"parking",
                "connection":"online",
                "state":0,
                "stragegy":"manual"
              }
            ]
          },
          {
            "number":4,
            "name":"Garagem G4",
            "controlled_lights":[
              {
                "id":"43e474db-c8c7-47d3-b479-14b5a39e80bb",
                "area":"Luz do hall de garagem",
                "type":"hall",
                "connection":"online",
                "state":0,
                "stragegy":"manual"
              },
              {
                "id":"8a4bac52-11ec-4842-aa8e-9e863b649615",
                "area":"Garagem G4",
                "type":"parking",
                "connection":"online",
                "state":0,
                "stragegy":"manual"
              }
            ]
          },
          {
            "number":5,
            "name":"5º andar",
            "controlled_lights":[
              {
                "id":"3fe6fcb4-1314-4fb0-a15b-2f8c77b16ac0",
                "area":"Luz do hall de apartamentos",
                "type":"hall",
                "connection":"online",
                "state":0,
                "stragegy":"manual"
              }
            ]
          },
          {
            "number":6,
            "name":"6º andar",
            "controlled_lights":[
              {
                "id":"8880d0b5-0d97-4974-98e9-450de291aec4",
                "area":"Luz do hall de apartamentos",
                "type":"hall",
                "connection":"online",
                "state":0,
                "stragegy":"manual"
              }
            ]
          }
        ]
      }
    ]
  }
}